README.rst
setup.cfg
setup.py
django_principals.egg-info/PKG-INFO
django_principals.egg-info/SOURCES.txt
django_principals.egg-info/dependency_links.txt
django_principals.egg-info/not-zip-safe
django_principals.egg-info/requires.txt
django_principals.egg-info/top_level.txt
principals/__init__.py
principals/fields.py
principals/managers.py
principals/models.py
principals/tests.py