Metadata-Version: 1.1
Name: django-principals
Version: 0.1.4
Summary: A Django field for defining a principal instance.
Home-page: http://github.com/mogga/django-principals
Author: Robert Moggach
Author-email: rob@moggach.com
License: UNKNOWN
Platform: UNKNOWN
Classifier: Development Status :: 3 - Alpha
Classifier: Environment :: Web Environment
Classifier: Intended Audience :: Developers
Classifier: License :: OSI Approved :: BSD License
Classifier: Operating System :: OS Independent
Classifier: Programming Language :: Python
Classifier: Framework :: Django
